anchcloud_sdk-0.0.1-py2.7-nspkg.pth
anchcloud/conn/__init__.py
anchcloud/conn/iaas_client.py
anchcloud/iaas/__init__.py
anchcloud/iaas/eips.py
anchcloud/iaas/errors.py
anchcloud/iaas/images.py
anchcloud/iaas/instances.py
anchcloud/iaas/job.py
anchcloud/iaas/keypairs.py
anchcloud/iaas/loadbalancers.py
anchcloud/iaas/routers.py
anchcloud/iaas/security_groups.py
anchcloud/iaas/snapshots.py
anchcloud/iaas/volumes.py
anchcloud/iaas/vxnets.py
anchcloud/misc/__init__.py
anchcloud/misc/utils.py
anchcloud_sdk-0.0.1.dist-info/DESCRIPTION.rst
anchcloud_sdk-0.0.1.dist-info/METADATA
anchcloud_sdk-0.0.1.dist-info/RECORD
anchcloud_sdk-0.0.1.dist-info/WHEEL
anchcloud_sdk-0.0.1.dist-info/metadata.json
anchcloud_sdk-0.0.1.dist-info/namespace_packages.txt
anchcloud_sdk-0.0.1.dist-info/top_level.txt
