Metadata-Version: 2.0
Name: anchcloud-sdk
Version: 0.0.1
Summary: Software Development Kit for AnchCloud.
Home-page: UNKNOWN
Author: chenyl
Author-email: chenyl@51idc.com
License: UNKNOWN
Keywords: anchcloud iaas qingstor sdk
Platform: UNKNOWN
Requires-Dist: datetime
Requires-Dist: oauth2
